sepadd/__init__.py
sepaxml/__init__.py
sepaxml/debit.py
sepaxml/shared.py
sepaxml/transfer.py
sepaxml/utils.py
sepaxml/validation.py
sepaxml/schemas/pain.001.001.01.xsd
sepaxml/schemas/pain.001.001.03.xsd
sepaxml/schemas/pain.001.003.01.xsd
sepaxml/schemas/pain.001.003.03.xsd
sepaxml/schemas/pain.008.001.02.xsd
sepaxml/schemas/pain.008.002.02.xsd
sepaxml/schemas/pain.008.003.02.xsd
sepaxml-2.6.1.dist-info/LICENSE
sepaxml-2.6.1.dist-info/METADATA
sepaxml-2.6.1.dist-info/WHEEL
sepaxml-2.6.1.dist-info/top_level.txt
sepaxml-2.6.1.dist-info/RECORD
