Metadata-Version: 2.1
Name: sepaxml
Version: 2.6.1
Summary: Python SEPA XML implementations
Home-page: https://github.com/raphaelm/python-sepaxml
Author: Raphael Michel
Author-email: mail@raphaelmichel.de
License: MIT License
Keywords: xml banking sepa
Classifier: Development Status :: 4 - Beta
Classifier: Intended Audience :: Developers
Classifier: Intended Audience :: Other Audience
Classifier: License :: OSI Approved :: MIT License
Classifier: Programming Language :: Python :: 3.4
Classifier: Programming Language :: Python :: 3.5
Classifier: Programming Language :: Python :: 3.6
License-File: LICENSE
Requires-Dist: xmlschema
Requires-Dist: text-unidecode
